[
    {
    "iTotalRecords": null,
    "iTotalDisplayRecords": null,
    "sEcho": null,
    "iDisplayStart": 0,
    "iDisplayLength": 10,
    "isQueryCount": true,
    "data": [],
    "user_id": null,
    "userId": 5,
    "orgId": 1,
    "orgIds": null,
    "userName": "admin",
    "userAccount": "admin",
    "authorizeCode": null,
    "pwdState": 1,
    "email": "shilr@iwangding.com",
    "telephone": "",
    "post": "",
    "state": 0,
    "createTime": 1493105687000,
    "seqNum": null,
    "address": "",
    "userPhoto": null,
    "roleId": null,
    "roleIds": null,
    "roleName": null,
    "orgName": null,
    "userIds": null,
    "stateName": "有效",
    "orgNames": null,
    "sex": 0,
    "sexName": "男"
  },
    {
    "iTotalRecords": null,
    "iTotalDisplayRecords": null,
    "sEcho": null,
    "iDisplayStart": 0,
    "iDisplayLength": 10,
    "isQueryCount": true,
    "data": [],
    "user_id": null,
    "userId": 6,
    "orgId": 1,
    "orgIds": null,
    "userName": "jsadmin",
    "userAccount": "jsadmin",
    "authorizeCode": null,
    "pwdState": 1,
    "email": "11@11.com",
    "telephone": "",
    "post": "",
    "state": 1,
    "createTime": 1498613418000,
    "seqNum": null,
    "address": "",
    "userPhoto": null,
    "roleId": null,
    "roleIds": null,
    "roleName": null,
    "orgName": null,
    "userIds": null,
    "stateName": "有效",
    "orgNames": null,
    "sex": 1,
    "sexName": "男"
  },
    {
    "iTotalRecords": null,
    "iTotalDisplayRecords": null,
    "sEcho": null,
    "iDisplayStart": 0,
    "iDisplayLength": 10,
    "isQueryCount": true,
    "data": [],
    "user_id": null,
    "userId": 20,
    "orgId": 1,
    "orgIds": null,
    "userName": "yanglx",
    "userAccount": "yanglx",
    "authorizeCode": null,
    "pwdState": 1,
    "email": "11@11.com",
    "telephone": "",
    "post": "",
    "state": 1,
    "createTime": 1504764076000,
    "seqNum": null,
    "address": "",
    "userPhoto": null,
    "roleId": null,
    "roleIds": null,
    "roleName": null,
    "orgName": null,
    "userIds": null,
    "stateName": "有效",
    "orgNames": null,
    "sex": 1,
    "sexName": "男"
  },
    {
    "iTotalRecords": null,
    "iTotalDisplayRecords": null,
    "sEcho": null,
    "iDisplayStart": 0,
    "iDisplayLength": 10,
    "isQueryCount": true,
    "data": [],
    "user_id": null,
    "userId": 21,
    "orgId": 1,
    "orgIds": null,
    "userName": "duxiang",
    "userAccount": "duxiang",
    "authorizeCode": null,
    "pwdState": 1,
    "email": "11@11.com",
    "telephone": "",
    "post": "",
    "state": 1,
    "createTime": 1504771654000,
    "seqNum": null,
    "address": "",
    "userPhoto": null,
    "roleId": null,
    "roleIds": null,
    "roleName": null,
    "orgName": null,
    "userIds": null,
    "stateName": "有效",
    "orgNames": null,
    "sex": 1,
    "sexName": "男"
  },
    {
    "iTotalRecords": null,
    "iTotalDisplayRecords": null,
    "sEcho": null,
    "iDisplayStart": 0,
    "iDisplayLength": 10,
    "isQueryCount": true,
    "data": [],
    "user_id": null,
    "userId": 22,
    "orgId": 1,
    "orgIds": null,
    "userName": "xieyun",
    "userAccount": "xieyun",
    "authorizeCode": null,
    "pwdState": 1,
    "email": "11@11.com",
    "telephone": "",
    "post": "",
    "state": 1,
    "createTime": 1504771688000,
    "seqNum": null,
    "address": "",
    "userPhoto": null,
    "roleId": null,
    "roleIds": null,
    "roleName": null,
    "orgName": null,
    "userIds": null,
    "stateName": "有效",
    "orgNames": null,
    "sex": 1,
    "sexName": "男"
  }
]

